COPYING
LICENSE
MANIFEST.in
setup.py
gpml2svg/__init__.py
gpml2svg/gpml2svg.py
gpml2svg.egg-info/PKG-INFO
gpml2svg.egg-info/SOURCES.txt
gpml2svg.egg-info/dependency_links.txt
gpml2svg.egg-info/entry_points.txt
gpml2svg.egg-info/requires.txt
gpml2svg.egg-info/top_level.txt