Metadata-Version: 1.1
Name: gpml2svg
Version: 0.2.0
Summary: Render GPML pathway markup to SVG from the commandline/Python.
Home-page: https://github.com/mfitzp/gpml2svg
Author: Martin Fitzpatrick
Author-email: martin.fitzpatrick@gmail.com
License: BSD
Download-URL: https://github.com/mfitzp/gpml2svg/zipball/master
Keywords: bioinformatics metabolomics signalling pathways research analysis science
Platform: UNKNOWN
Classifier: Development Status :: 4 - Beta
Classifier: Natural Language :: English
Classifier: Operating System :: OS Independent
Classifier: Programming Language :: Python :: 2
Classifier: License :: OSI Approved :: BSD License
Classifier: Topic :: Scientific/Engineering :: Bio-Informatics
Classifier: Topic :: Education
Classifier: Intended Audience :: Science/Research
Classifier: Intended Audience :: Education
